clean_loop/__init__.py
clean_loop/cli.py
clean_loop-0.0.2.dist-info/LICENSE-APACHE.md
clean_loop-0.0.2.dist-info/LICENSE-MIT.md
clean_loop-0.0.2.dist-info/METADATA
clean_loop-0.0.2.dist-info/WHEEL
clean_loop-0.0.2.dist-info/entry_points.txt
clean_loop-0.0.2.dist-info/top_level.txt
clean_loop-0.0.2.dist-info/RECORD
