Metadata-Version: 2.1
Name: clean-loop
Version: 0.0.2
Summary: Repeat a script every given number of seconds
Home-page: https://github.com/MolassesLover/CleanLoop
Author: MolassesLover
Author-email: 60114762+MolassesLover@users.noreply.github.com
License: MIT
Platform: UNKNOWN
License-File: LICENSE-APACHE.md
License-File: LICENSE-MIT.md
Requires-Dist: colorama
